MANIFEST.in
README.rst
setup.py
sudocabulary/.vocab
sudocabulary/.vocabscript
sudocabulary/__init__.py
sudocabulary/install_entry.py
sudocabulary/script.sh
sudocabulary.egg-info/PKG-INFO
sudocabulary.egg-info/SOURCES.txt
sudocabulary.egg-info/dependency_links.txt
sudocabulary.egg-info/not-zip-safe
sudocabulary.egg-info/top_level.txt