Metadata-Version: 1.0
Name: sudocabulary
Version: 1.0.5
Summary: Combine your love for terminal with the love for learning English Vocabulary
Home-page: https://github.com/badarsh2/Sudocabulary
Author: badarsh2
Author-email: badarsh2@gmail.com
License: Apache-2.0
Platform: UNKNOWN
